README.rst
setup.py
production_rest_client/__init__.py
production_rest_client/api.py
production_rest_client/db_client.py
production_rest_client/rest_client.py
production_rest_client.egg-info/PKG-INFO
production_rest_client.egg-info/SOURCES.txt
production_rest_client.egg-info/dependency_links.txt
production_rest_client.egg-info/requires.txt
production_rest_client.egg-info/top_level.txt
production_rest_client/resources/__init__.py
production_rest_client/resources/benchmark_db_resource.py
production_rest_client/resources/benchmark_resource.py
production_rest_client/resources/delete_old_data.py
production_rest_client/resources/env_db_resource.py
production_rest_client/resources/firmware_build_resource.py
production_rest_client/resources/git_resource.py
production_rest_client/resources/oakgate_resource.py
production_rest_client/resources/operation_resource.py
production_rest_client/resources/remote_resource.py
production_rest_client/resources/state_resource.py
production_rest_client/resources/stop_flag_resource.py
production_rest_client/resources/test_db_resource.py
production_rest_client/resources/test_resource.py
production_rest_client/resources/upgrade_resource.py
production_rest_client/resources/models/__init__.py
production_rest_client/resources/models/database.py
production_rest_client/resources/models/database1.py
production_rest_client/resources/models/ftp_client.py
production_rest_client/resources/models/helper.py
production_rest_client/resources/models/remoter.py