Metadata-Version: 1.1
Name: production-rest-client
Version: 2.5.6
Summary: REST Runner
Home-page: https://pypi.org/project/production_rest_client
Author: weili.han
Author-email: 826338726@qq.com
License: MIT License
Keywords: runner,client
Platform: any
Classifier: Development Status :: 3 - Alpha
Classifier: Intended Audience :: Developers
Classifier: Topic :: Software Development :: Libraries
Classifier: License :: OSI Approved :: MIT License
Classifier: Programming Language :: Python :: 3.6
